type2sql/__init__.py
type2sql/gen.py
type2sql/meta.py
type2sql/py.typed
type2sql/pytype.py
type2sql/sqlcol.py
type2sql/type_info.py
type2sql-0.1.0.dist-info/METADATA
type2sql-0.1.0.dist-info/WHEEL
type2sql-0.1.0.dist-info/top_level.txt
type2sql-0.1.0.dist-info/RECORD
