Metadata-Version: 2.4
Name: type2sql
Version: 0.1.0
Summary: Code generator for Python classes to flattened relational SQL Table types
Author-email: Paresh Adhia <padhia@gmail.com>
Classifier: Programming Language :: Python :: 3
Requires-Python: >=3.12
